MANIFEST.in
README.rst
cached_version.json
development.ini
setup.cfg
setup.py
nozama/__init__.py
nozama/cloudsearch/__init__.py
nozama/cloudsearch/service/__init__.py
nozama/cloudsearch/service/nozamaviews.py
nozama/cloudsearch/service/restfulhelpers.py
nozama/cloudsearch/service/views.py
nozama/cloudsearch/service/docs/__init__.py
nozama/cloudsearch/service/docs/api.html
nozama/cloudsearch/service/docs/developer.html
nozama/cloudsearch/service/docs/genindex.html
nozama/cloudsearch/service/docs/index.html
nozama/cloudsearch/service/docs/search.html
nozama/cloudsearch/service/docs/searchindex.js
nozama/cloudsearch/service/docs/_sources/api.txt
nozama/cloudsearch/service/docs/_sources/developer.txt
nozama/cloudsearch/service/docs/_sources/index.txt
nozama/cloudsearch/service/docs/_static/ajax-loader.gif
nozama/cloudsearch/service/docs/_static/api.html
nozama/cloudsearch/service/docs/_static/basic.css
nozama/cloudsearch/service/docs/_static/comment-bright.png
nozama/cloudsearch/service/docs/_static/comment-close.png
nozama/cloudsearch/service/docs/_static/comment.png
nozama/cloudsearch/service/docs/_static/default.css
nozama/cloudsearch/service/docs/_static/developer.html
nozama/cloudsearch/service/docs/_static/doctools.js
nozama/cloudsearch/service/docs/_static/down-pressed.png
nozama/cloudsearch/service/docs/_static/down.png
nozama/cloudsearch/service/docs/_static/file.png
nozama/cloudsearch/service/docs/_static/genindex.html
nozama/cloudsearch/service/docs/_static/index.html
nozama/cloudsearch/service/docs/_static/jquery.js
nozama/cloudsearch/service/docs/_static/minus.png
nozama/cloudsearch/service/docs/_static/plus.png
nozama/cloudsearch/service/docs/_static/pygments.css
nozama/cloudsearch/service/docs/_static/search.html
nozama/cloudsearch/service/docs/_static/searchindex.js
nozama/cloudsearch/service/docs/_static/searchtools.js
nozama/cloudsearch/service/docs/_static/sidebar.js
nozama/cloudsearch/service/docs/_static/underscore.js
nozama_cloudsearch_service.egg-info/PKG-INFO
nozama_cloudsearch_service.egg-info/SOURCES.txt
nozama_cloudsearch_service.egg-info/dependency_links.txt
nozama_cloudsearch_service.egg-info/eager_resources.txt
nozama_cloudsearch_service.egg-info/entry_points.txt
nozama_cloudsearch_service.egg-info/namespace_packages.txt
nozama_cloudsearch_service.egg-info/not-zip-safe
nozama_cloudsearch_service.egg-info/requires.txt
nozama_cloudsearch_service.egg-info/top_level.txt