Metadata-Version: 1.0
Name: nozama-cloudsearch-service
Version: 1.0.4
Summary: A REST service which implements the Amazon CloudSearch for local testing purposes. This is *not* intended as a replacement for Amazon CloudSearch.See the http://nozama-cloudsearch.readthedocs.org/en/latest/ for more details.
Home-page: https://github.com/oisinmulvihill/nozama-cloudsearch
Author: Oisin Mulvihill
Author-email: oisin dot mulvihill a-t  gmail dot com
License: BSD
Keywords: web wsgi bfg pylons pyramid
Platform: UNKNOWN
Classifier: Programming Language :: Python
Classifier: Framework :: Pylons
Classifier: Topic :: Internet :: WWW/HTTP
Classifier: Topic :: Internet :: WWW/HTTP :: WSGI :: Application
